Metadata-Version: 2.1
Name: amharic-keyboard
Version: 0.0.4
Summary: A package to type amharic letters
Home-page: https://github.com/magna25/amharic-keyboard
Author: Henok Hailemariam
Author-email: henny.bog@gmail.com
License: UNKNOWN
Download-URL: https://github.com/magna25/amharic-keyboard/archive/0.0.4.tar.gz
Platform: UNKNOWN
Classifier: Programming Language :: Python :: 3
Classifier: License :: OSI Approved :: MIT License
Classifier: Operating System :: OS Independent
